{
    "data": [
        {
            "id": 35,
            "slapCount": "0",
            "vid": "443",
            "stickerId": "27",
            "subgraphEntityId": "0x4219c3d837889086b4205534e8e22e652620dc65df2e33491aba72d5f0b2a70707000000",
            "originalPublisher": "0xb3aaee282e66ebcd9ad10cd4af5a76fe94cdab79",
            "currentPublisher": "0xb3aaee282e66ebcd9ad10cd4af5a76fe94cdab79",
            "payoutAddress": "0xb3aaee282e66ebcd9ad10cd4af5a76fe94cdab79",
            "publishedAt": "2025-04-08T19:31:06.821Z",
            "price": "1000000000000000",
            "paymentMethodId": "1",
            "limitToHolders": null,
            "limit": "0",
            "endTime": null,
            "metadataCID": "QmUygqtJE6LB1JNCCCoFT3TxQPzoAmwab1GBeKGPEyA85T",
            "metadataLoaded": true,
            "name": "Blitmap 3",
            "imageCID": "QmX996vvs2ksCEpXMNaaDTz7WkF2HiRhAR7nrFQsdtr58D",
            "filename": "Blitmap 3.png",
            "contentType": "image/png",
            "aspectRatio": "1",
            "size": "112992",
            "url": "https://www.blitmap.com/",
            "description": "",
            "originalPublisherEns": null,
            "currentPublisherEns": null
        },
        {
            "id": 34,
            "slapCount": "1",
            "vid": "410",
            "stickerId": "26",
            "subgraphEntityId": "0x25699f9c97b5ec47ad133f3205580444489460a62ffe75dbb698f1343d0603a701000000",
            "originalPublisher": "0x7c987f43355e7ef8bdc72063a78d579ae205d741",
            "currentPublisher": "0x7c987f43355e7ef8bdc72063a78d579ae205d741",
            "payoutAddress": "0x7c987f43355e7ef8bdc72063a78d579ae205d741",
            "publishedAt": "2025-04-07T19:12:04.514Z",
            "price": "0",
            "paymentMethodId": "0",
            "limitToHolders": null,
            "limit": "0",
            "endTime": null,
            "metadataCID": "QmWPxFKqAmAbUdVmDbNAh7YiNe6KPYWqW4SpgpxPS94A3C",
            "metadataLoaded": true,
            "name": "Blitmap 26 Cheese",
            "imageCID": "QmeB5FmWnJ6Rmv5UxAnKqqwFp5jvTSWgpUJ2pm3bP6NuVx",
            "filename": "Blitmap 26 Cheese.png",
            "contentType": "image/png",
            "aspectRatio": "1",
            "size": "63595",
            "url": "https://www.blitmap.com/",
            "description": "",
            "originalPublisherEns": null,
            "currentPublisherEns": null
        },
        {
            "id": 33,
            "slapCount": "1",
            "vid": "409",
            "stickerId": "25",
            "subgraphEntityId": "0x6183ec4d3f265ffc298ec30f929329fe48867e36f19488599e91021d669f98e81b000000",
            "originalPublisher": "0x7c987f43355e7ef8bdc72063a78d579ae205d741",
            "currentPublisher": "0x7c987f43355e7ef8bdc72063a78d579ae205d741",
            "payoutAddress": "0x7c987f43355e7ef8bdc72063a78d579ae205d741",
            "publishedAt": "2025-04-07T19:10:04.053Z",
            "price": "0",
            "paymentMethodId": "0",
            "limitToHolders": null,
            "limit": "0",
            "endTime": null,
            "metadataCID": "QmPG1MvcegcoiU9gT72j2ZcCaAVSwpJStXT73tjbWjHd6o",
            "metadataLoaded": true,
            "name": "Blitmap 456 Atlantis Vanilla",
            "imageCID": "QmP9TcAhkFyg7ZiQSST55fsytE6hdv1H8Cr3nWu2vkTpxP",
            "filename": "Blitmap 456 Atlantis Vanilla.png",
            "contentType": "image/png",
            "aspectRatio": "1.01",
            "size": "75878",
            "url": "https://www.blitmap.com/",
            "description": "",
            "originalPublisherEns": null,
            "currentPublisherEns": null
        },
        {
            "id": 32,
            "slapCount": "1",
            "vid": "408",
            "stickerId": "24",
            "subgraphEntityId": "0x56fb909422e31dc520eb5795046f63bab17ef381364b0ae44b07e6fa31f941d869000000",
            "originalPublisher": "0x7c987f43355e7ef8bdc72063a78d579ae205d741",
            "currentPublisher": "0x7c987f43355e7ef8bdc72063a78d579ae205d741",
            "payoutAddress": "0x7c987f43355e7ef8bdc72063a78d579ae205d741",
            "publishedAt": "2025-04-07T19:08:51.506Z",
            "price": "0",
            "paymentMethodId": "0",
            "limitToHolders": null,
            "limit": "0",
            "endTime": null,
            "metadataCID": "QmadxXb5LwH4F3UpQhXhQuCCebZXLQLHaPEhQj56LTumAn",
            "metadataLoaded": true,
            "name": "Blitmap 988",
            "imageCID": "QmcxDcVTy96X47j16nhkufYLDbVgV63rASEnDAvcLEa9wR",
            "filename": "Blitmap 988.png",
            "contentType": "image/png",
            "aspectRatio": "1",
            "size": "52835",
            "url": "https://www.blitmap.com/",
            "description": "",
            "originalPublisherEns": null,
            "currentPublisherEns": null
        },
        {
            "id": 31,
            "slapCount": "1",
            "vid": "407",
            "stickerId": "23",
            "subgraphEntityId": "0x45de44e3b6632d4f28a7670fad16b3fc20bffdff6b29812a53e21ce94e79574594000000",
            "originalPublisher": "0xebe4b33f9e2abb47a042a2cb9f45698dcae91e17",
            "currentPublisher": "0xebe4b33f9e2abb47a042a2cb9f45698dcae91e17",
            "payoutAddress": "0xebe4b33f9e2abb47a042a2cb9f45698dcae91e17",
            "publishedAt": "2025-04-07T19:06:16.012Z",
            "price": "0",
            "paymentMethodId": "0",
            "limitToHolders": null,
            "limit": "0",
            "endTime": null,
            "metadataCID": "QmQr1hGY6kN3uAmmh6eZ4vNgQf3Cxr9b3yxsQ4Mw3FGhxP",
            "metadataLoaded": true,
            "name": "Blitmap 82 ",
            "imageCID": "Qmc99xsQm8C52aeT234XJ9Lt6AWqXUSSJyT8Gf2xXrnYtA",
            "filename": "Blitmap 82 .png",
            "contentType": "image/png",
            "aspectRatio": "1.01",
            "size": "61286",
            "url": "https://www.blitmap.com/",
            "description": "",
            "originalPublisherEns": null,
            "currentPublisherEns": null
        },
        {
            "id": 30,
            "slapCount": "2",
            "vid": "374",
            "stickerId": "22",
            "subgraphEntityId": "0x9445c2d7616ad9935c6dbf52c941909596f037bc175fb0f0ab8f178977c5335947000000",
            "originalPublisher": "0xebe4b33f9e2abb47a042a2cb9f45698dcae91e17",
            "currentPublisher": "0xebe4b33f9e2abb47a042a2cb9f45698dcae91e17",
            "payoutAddress": "0xebe4b33f9e2abb47a042a2cb9f45698dcae91e17",
            "publishedAt": "2025-03-24T15:37:04.556Z",
            "price": "0",
            "paymentMethodId": "0",
            "limitToHolders": null,
            "limit": "0",
            "endTime": null,
            "metadataCID": "QmQfVurhfLrymEbpqvuHSTnqaCnMfgPhukbn4aAfu41mwz",
            "metadataLoaded": true,
            "name": "Blitmap 130",
            "imageCID": "QmXUf5M8R7fUXzj22tHE3h89uUSu5cmL5h4ddddZaLS23e",
            "filename": "Blitmap 130.png",
            "contentType": "image/png",
            "aspectRatio": "1",
            "size": "166416",
            "url": "https://www.blitmap.com/",
            "description": "",
            "originalPublisherEns": null,
            "currentPublisherEns": null
        },
        {
            "id": 29,
            "slapCount": "2",
            "vid": "341",
            "stickerId": "21",
            "subgraphEntityId": "0xf13e875ab87d213ed9f527d4b94e7ac2b4bc1b0b5215dac5777b4d469d6fb143b4000000",
            "originalPublisher": "0xebe4b33f9e2abb47a042a2cb9f45698dcae91e17",
            "currentPublisher": "0xebe4b33f9e2abb47a042a2cb9f45698dcae91e17",
            "payoutAddress": "0xebe4b33f9e2abb47a042a2cb9f45698dcae91e17",
            "publishedAt": "2025-03-22T15:24:17.564Z",
            "price": "0",
            "paymentMethodId": "0",
            "limitToHolders": null,
            "limit": "0",
            "endTime": null,
            "metadataCID": "QmSd5QqF1afCaHgmya2xmyXcBgZBvhrwfugvnruz3JnWSf",
            "metadataLoaded": true,
            "name": "Blitmap 137",
            "imageCID": "QmPxez8HwUE4GwZDDidFTCB49QfEQRvDwiVqDMQLYNa1Nv",
            "filename": "Blitmap 137.png",
            "contentType": "image/png",
            "aspectRatio": "1",
            "size": "92483",
            "url": "https://www.blitmap.com",
            "description": "",
            "originalPublisherEns": null,
            "currentPublisherEns": null
        },
        {
            "id": 28,
            "slapCount": "1",
            "vid": "340",
            "stickerId": "20",
            "subgraphEntityId": "0xe8ff395b0d03a9e1a700f448d0d59503fad0c33886c749b85486fb706a53db3760000000",
            "originalPublisher": "0xebe4b33f9e2abb47a042a2cb9f45698dcae91e17",
            "currentPublisher": "0xebe4b33f9e2abb47a042a2cb9f45698dcae91e17",
            "payoutAddress": "0xebe4b33f9e2abb47a042a2cb9f45698dcae91e17",
            "publishedAt": "2025-03-22T15:11:38.093Z",
            "price": "0",
            "paymentMethodId": "0",
            "limitToHolders": null,
            "limit": "0",
            "endTime": null,
            "metadataCID": "QmcHzKgNeRnVsdNPfvPnAnsH6Ndog7cKdmD48vuh3rek9B",
            "metadataLoaded": true,
            "name": "Blitmap 5",
            "imageCID": "QmRZ9w5JvfeAWgufx3LZySxJsw4fzsVF2YTqdEwu4CrJ7A",
            "filename": "Blitmap 5.png",
            "contentType": "image/png",
            "aspectRatio": "1.01",
            "size": "76822",
            "url": "https://www.blitmap.com/",
            "description": "",
            "originalPublisherEns": null,
            "currentPublisherEns": null
        },
        {
            "id": 27,
            "slapCount": "0",
            "vid": "339",
            "stickerId": "19",
            "subgraphEntityId": "0xdce122cd421e342fb277f65c5470ae8cc62d2a2909c6d6437d3209b0b5d64ddd0b010000",
            "originalPublisher": "0xebe4b33f9e2abb47a042a2cb9f45698dcae91e17",
            "currentPublisher": "0xebe4b33f9e2abb47a042a2cb9f45698dcae91e17",
            "payoutAddress": "0xebe4b33f9e2abb47a042a2cb9f45698dcae91e17",
            "publishedAt": "2025-03-22T14:55:29.899Z",
            "price": "0",
            "paymentMethodId": "0",
            "limitToHolders": null,
            "limit": "0",
            "endTime": null,
            "metadataCID": "QmWt8N4mosnRa8wim3k1HNpEy1ANM2tguBDNHyqSbZsL8j",
            "metadataLoaded": true,
            "name": "Blitmap 2",
            "imageCID": "Qmak6mg1VfKQCgKoU3WYPJ2aJEB5u1PK5KJ4FmBBs7SYvp",
            "filename": "Blitmap 2.png",
            "contentType": "image/png",
            "aspectRatio": "1",
            "size": "113776",
            "url": "https://www.blitmap.com",
            "description": "",
            "originalPublisherEns": null,
            "currentPublisherEns": null
        },
        {
            "id": 26,
            "slapCount": "2",
            "vid": "306",
            "stickerId": "18",
            "subgraphEntityId": "0x9372333a3aa734a1527333cbd1200b009047fa550a25ddafa2bd504327422cf53b010000",
            "originalPublisher": "0xebe4b33f9e2abb47a042a2cb9f45698dcae91e17",
            "currentPublisher": "0xebe4b33f9e2abb47a042a2cb9f45698dcae91e17",
            "payoutAddress": "0xebe4b33f9e2abb47a042a2cb9f45698dcae91e17",
            "publishedAt": "2025-03-12T15:17:30.476Z",
            "price": "0",
            "paymentMethodId": "0",
            "limitToHolders": null,
            "limit": "0",
            "endTime": null,
            "metadataCID": "QmevjE8nRdGzus33pBuzMRLiBegzYYoMEPbov4AVu3CyQM",
            "metadataLoaded": true,
            "name": "Allstarz 7599",
            "imageCID": "QmRG9ujFPVc2v2ySkHLBfNK257ENGfvNmkaAu8ftAoyTYS",
            "filename": "Allstarz 7599.jpg",
            "contentType": "image/jpeg",
            "aspectRatio": "1",
            "size": "293920",
            "url": "https://www.opensea.com",
            "description": "",
            "originalPublisherEns": null,
            "currentPublisherEns": null
        },
        {
            "id": 25,
            "slapCount": "1",
            "vid": "273",
            "stickerId": "17",
            "subgraphEntityId": "0x426d837447510b8b12802f407029e990e0d4c093cbc7093380cc01ae3de1c7db86000000",
            "originalPublisher": "0x7c987f43355e7ef8bdc72063a78d579ae205d741",
            "currentPublisher": "0x7c987f43355e7ef8bdc72063a78d579ae205d741",
            "payoutAddress": "0x7c987f43355e7ef8bdc72063a78d579ae205d741",
            "publishedAt": "2025-02-21T17:46:43.811Z",
            "price": "0",
            "paymentMethodId": "0",
            "limitToHolders": null,
            "limit": "0",
            "endTime": null,
            "metadataCID": "QmPtSt8ATjn4CHbAiDiGD1MsxL3U2HXbsxi1zG2AeW39hi",
            "metadataLoaded": true,
            "name": "Noun 8",
            "imageCID": "QmXCNCuAioZvnD6e9x48eAyuqaegm8kgQ4hci6Ppxf9XGe",
            "filename": "Noun 8.png",
            "contentType": "image/png",
            "aspectRatio": "1",
            "size": "81027",
            "url": "",
            "description": "",
            "originalPublisherEns": null,
            "currentPublisherEns": null
        },
        {
            "id": 22,
            "slapCount": "1",
            "vid": "206",
            "stickerId": "14",
            "subgraphEntityId": "0x4c21a06477aacff548c13598d880d9f64d697fb41d9933cf5031bee15d22ba3d3f000000",
            "originalPublisher": "0x7c987f43355e7ef8bdc72063a78d579ae205d741",
            "currentPublisher": "0x7c987f43355e7ef8bdc72063a78d579ae205d741",
            "payoutAddress": "0x7c987f43355e7ef8bdc72063a78d579ae205d741",
            "publishedAt": "2025-01-31T05:18:26.479Z",
            "price": "0",
            "paymentMethodId": "0",
            "limitToHolders": null,
            "limit": "0",
            "endTime": null,
            "metadataCID": "QmeGPWntvvPDuVqHgd5UaWazCRAmqPdJSa9L3mtZj3VMfW",
            "metadataLoaded": true,
            "name": "Noun 8",
            "imageCID": "QmXCNCuAioZvnD6e9x48eAyuqaegm8kgQ4hci6Ppxf9XGe",
            "filename": "Noun 8.png",
            "contentType": "image/png",
            "aspectRatio": "1",
            "size": "81027",
            "url": "https://nouns.wtf/",
            "description": "",
            "originalPublisherEns": null,
            "currentPublisherEns": null
        },
        {
            "id": 21,
            "slapCount": "2",
            "vid": "205",
            "stickerId": "13",
            "subgraphEntityId": "0x18d341533f500bbba2fb6697f8cd5c4a27ef66bacef380a83981b5268cdbc94940000000",
            "originalPublisher": "0x7c987f43355e7ef8bdc72063a78d579ae205d741",
            "currentPublisher": "0x7c987f43355e7ef8bdc72063a78d579ae205d741",
            "payoutAddress": "0x7c987f43355e7ef8bdc72063a78d579ae205d741",
            "publishedAt": "2025-01-31T04:58:54.632Z",
            "price": "0",
            "paymentMethodId": "0",
            "limitToHolders": null,
            "limit": "0",
            "endTime": null,
            "metadataCID": "QmSRK2rhsiitBvjfvf2H5MmdrDuG7ag2XuAWxcihU71jo4",
            "metadataLoaded": true,
            "name": "Noun 2",
            "imageCID": "QmT33PQnkWH92t79ukJ4SS16i6PnCn1rrBJEiRTQXZWgDk",
            "filename": "Noun 2.png",
            "contentType": "image/png",
            "aspectRatio": "1",
            "size": "76815",
            "url": "https://nouns.wtf/",
            "description": "",
            "originalPublisherEns": null,
            "currentPublisherEns": null
        },
        {
            "id": 10,
            "slapCount": "4",
            "vid": "1",
            "stickerId": "12",
            "subgraphEntityId": null,
            "originalPublisher": "0x6EBd8991fC87F130DE28DE4b37F882d6cbE9aB28",
            "currentPublisher": "0x6EBd8991fC87F130DE28DE4b37F882d6cbE9aB28",
            "payoutAddress": "0x6EBd8991fC87F130DE28DE4b37F882d6cbE9aB28",
            "publishedAt": "2025-01-15T15:13:18.000Z",
            "price": "0",
            "paymentMethodId": "0",
            "limitToHolders": null,
            "limit": null,
            "endTime": null,
            "metadataCID": "QmfHBHAuBfshNnAp9JX3pC9eqH5VDRL68vN2PvEExkLe8d",
            "metadataLoaded": true,
            "name": "Everything",
            "imageCID": "QmTCuUA4N365nwjS8yevbGaNXPj47vkhDbHArFfuggy91U",
            "filename": "Everything.png",
            "contentType": "image/png",
            "aspectRatio": "1",
            "size": "1992",
            "url": "EverythingIsEverything.NYC",
            "description": "Everything Is Everything",
            "originalPublisherEns": "varley.eth",
            "currentPublisherEns": "varley.eth"
        },
        {
            "id": 9,
            "slapCount": "2",
            "vid": "1",
            "stickerId": "11",
            "subgraphEntityId": null,
            "originalPublisher": "0xebE4b33f9E2abb47A042A2CB9f45698DCae91E17",
            "currentPublisher": "0xebE4b33f9E2abb47A042A2CB9f45698DCae91E17",
            "payoutAddress": "0xebE4b33f9E2abb47A042A2CB9f45698DCae91E17",
            "publishedAt": "2024-12-29T05:26:44.000Z",
            "price": "0",
            "paymentMethodId": "0",
            "limitToHolders": null,
            "limit": null,
            "endTime": null,
            "metadataCID": "Qmbx1QSrFnNe3PBFJe8yKE82GXJxmwu3jFioYhUuNK5tJ9",
            "metadataLoaded": true,
            "name": "Blitmap 2",
            "imageCID": "Qmak6mg1VfKQCgKoU3WYPJ2aJEB5u1PK5KJ4FmBBs7SYvp",
            "filename": "Blitmap 2.png",
            "contentType": "image/png",
            "aspectRatio": "1",
            "size": "113776",
            "url": "https://www.blitmap.com",
            "description": "Blitmap is a community crafted sci-fantasy universe based on CC0 pixel art.",
            "originalPublisherEns": "ivyroot.eth",
            "currentPublisherEns": "ivyroot.eth"
        },
        {
            "id": 6,
            "slapCount": "5",
            "vid": "1",
            "stickerId": "8",
            "subgraphEntityId": null,
            "originalPublisher": "0xF73FE15cFB88ea3C7f301F16adE3c02564ACa407",
            "currentPublisher": "0xF73FE15cFB88ea3C7f301F16adE3c02564ACa407",
            "payoutAddress": "0xF73FE15cFB88ea3C7f301F16adE3c02564ACa407",
            "publishedAt": "2024-12-23T19:40:16.000Z",
            "price": "0",
            "paymentMethodId": "0",
            "limitToHolders": null,
            "limit": null,
            "endTime": null,
            "metadataCID": "QmdGLLoff5Dd62E8yhzBjAxvQDM7yhfTjeDsptU3AMtRJc",
            "metadataLoaded": true,
            "name": "mannybrain",
            "imageCID": "QmSEgUPuCZKsATihYYRBzLYSJ9Fqn1AAdsUyP8Y3aMLYWg",
            "filename": "mannybrain.png",
            "contentType": "image/png",
            "aspectRatio": "1",
            "size": "159854",
            "url": "",
            "description": "",
            "originalPublisherEns": "shahruz.eth",
            "currentPublisherEns": "shahruz.eth"
        },
        {
            "id": 5,
            "slapCount": "5",
            "vid": "1",
            "stickerId": "7",
            "subgraphEntityId": null,
            "originalPublisher": "0x355Fe8B1D00dbAE26F7b265Ef6990a2e2930C93c",
            "currentPublisher": "0x355Fe8B1D00dbAE26F7b265Ef6990a2e2930C93c",
            "payoutAddress": "0x355Fe8B1D00dbAE26F7b265Ef6990a2e2930C93c",
            "publishedAt": "2024-12-18T05:40:28.000Z",
            "price": "0",
            "paymentMethodId": "0",
            "limitToHolders": null,
            "limit": null,
            "endTime": null,
            "metadataCID": "QmVzu83VfD86EfPJgHpfxrHHriJaCSiBWzaadHdTwqoCBM",
            "metadataLoaded": true,
            "name": "Manny",
            "imageCID": "QmfZuqYKqYzLArYQY3eF6o55CzGUzenJ4rTVhuAbjJPGpv",
            "filename": "Manny.png",
            "contentType": "image/png",
            "aspectRatio": "0.96",
            "size": "352373",
            "url": "",
            "description": "",
            "originalPublisherEns": null,
            "currentPublisherEns": null
        },
        {
            "id": 4,
            "slapCount": "7",
            "vid": "1",
            "stickerId": "6",
            "subgraphEntityId": null,
            "originalPublisher": "0x9470B8C2ddc2d25f2d04cD92b15490227B2CCE15",
            "currentPublisher": "0x9470B8C2ddc2d25f2d04cD92b15490227B2CCE15",
            "payoutAddress": "0x9470B8C2ddc2d25f2d04cD92b15490227B2CCE15",
            "publishedAt": "2024-12-18T04:55:30.000Z",
            "price": "0",
            "paymentMethodId": "0",
            "limitToHolders": null,
            "limit": null,
            "endTime": null,
            "metadataCID": "QmcpaNpWW2qoqpMc44G4YP24VMzgGTH1vhwURUGPsDP4b5",
            "metadataLoaded": true,
            "name": "Blitmap 33",
            "imageCID": "QmP9P3uoEpMSJ8SX7joF8e9vm5GRsXqNxAfzejDgkcqQdT",
            "filename": "Blitmap 33.png",
            "contentType": "image/png",
            "aspectRatio": "1",
            "size": "107042",
            "url": "",
            "description": "",
            "originalPublisherEns": null,
            "currentPublisherEns": null
        },
        {
            "id": 3,
            "slapCount": "4",
            "vid": "1",
            "stickerId": "5",
            "subgraphEntityId": null,
            "originalPublisher": "0x9470B8C2ddc2d25f2d04cD92b15490227B2CCE15",
            "currentPublisher": "0x9470B8C2ddc2d25f2d04cD92b15490227B2CCE15",
            "payoutAddress": "0x9470B8C2ddc2d25f2d04cD92b15490227B2CCE15",
            "publishedAt": "2024-12-18T04:55:08.000Z",
            "price": "0",
            "paymentMethodId": "0",
            "limitToHolders": null,
            "limit": null,
            "endTime": null,
            "metadataCID": "QmNP6AzqdpbVvsZbQQQXCzzayANdELFVjR8msCK2F7f2MW",
            "metadataLoaded": true,
            "name": "Blitmap 1",
            "imageCID": "QmP4nqrBYa3dbZUVzwRCMwL7mF2W1AGbboSfivY9AzkWNk",
            "filename": "Blitmap 1.png",
            "contentType": "image/png",
            "aspectRatio": "1",
            "size": "108040",
            "url": "",
            "description": "",
            "originalPublisherEns": null,
            "currentPublisherEns": null
        },
        {
            "id": 2,
            "slapCount": "3",
            "vid": "1",
            "stickerId": "4",
            "subgraphEntityId": null,
            "originalPublisher": "0x9470B8C2ddc2d25f2d04cD92b15490227B2CCE15",
            "currentPublisher": "0x9470B8C2ddc2d25f2d04cD92b15490227B2CCE15",
            "payoutAddress": "0x9470B8C2ddc2d25f2d04cD92b15490227B2CCE15",
            "publishedAt": "2024-12-18T04:53:44.000Z",
            "price": "0",
            "paymentMethodId": "0",
            "limitToHolders": null,
            "limit": null,
            "endTime": null,
            "metadataCID": "Qmf6FRRwrQV2BywuvpVP2g6j5LmpRX2AERvkcjuG7QYTPd",
            "metadataLoaded": true,
            "name": "Blitmap 0",
            "imageCID": "QmZHqPrcN9vj4nktdXeMB5X9w8hojuTH44jNWVRvh1Z9GF",
            "filename": "Blitmap 0.png",
            "contentType": "image/png",
            "aspectRatio": "1",
            "size": "76611",
            "url": "",
            "description": "",
            "originalPublisherEns": null,
            "currentPublisherEns": null
        },
        {
            "id": 1,
            "slapCount": "2",
            "vid": "1",
            "stickerId": "3",
            "subgraphEntityId": null,
            "originalPublisher": "0xdD0518b80c14f5EA49f95318e664b2d49e66cBad",
            "currentPublisher": "0xdD0518b80c14f5EA49f95318e664b2d49e66cBad",
            "payoutAddress": "0xdD0518b80c14f5EA49f95318e664b2d49e66cBad",
            "publishedAt": "2024-12-17T05:40:30.000Z",
            "price": "0",
            "paymentMethodId": "0",
            "limitToHolders": null,
            "limit": null,
            "endTime": null,
            "metadataCID": "QmS1omLvxFojxeNyuNXE6MXbVLZ77kn6ofjZnRmx7GWpuq",
            "metadataLoaded": true,
            "name": "Noun 0",
            "imageCID": "Qmc4g1xp7G6nvrBvYxEzT6yu9RDz9XdWT6mGz81mhKx7wX",
            "filename": "Noun 0.png",
            "contentType": "image/png",
            "aspectRatio": "1",
            "size": "74104",
            "url": "",
            "description": "",
            "originalPublisherEns": null,
            "currentPublisherEns": null
        }
    ]
}